LICENSE
README.md
setup.cfg
setup.py
pyraysum/__init__.py
pyraysum/doc.py
pyraysum/frs.py
pyraysum/plot.py
pyraysum/prs.py
pyraysum.egg-info/PKG-INFO
pyraysum.egg-info/SOURCES.txt
pyraysum.egg-info/dependency_links.txt
pyraysum.egg-info/requires.txt
pyraysum.egg-info/top_level.txt
pyraysum/examples/Notebooks/1_make_seismograms.ipynb
pyraysum/examples/Notebooks/2_reproduce_Porter-2011.ipynb
pyraysum/examples/Notebooks/3_invert_rf.ipynb
pyraysum/examples/data/model_Porter2011_aniso.txt
pyraysum/examples/data/model_Porter2011_dip.txt
pyraysum/examples/data/rf_hyb.dat
pyraysum/examples/data/telewavesim_aniso_baz150-slow006.dat
pyraysum/examples/data/telewavesim_baz090-slow006.dat
pyraysum/examples/notebooks/1_make_seismograms.ipynb
pyraysum/examples/notebooks/2_reproduce_Porter-2011.ipynb
pyraysum/examples/notebooks/3_invert_rf.ipynb
pyraysum/src/__init__.py
pyraysum/src/buildmodel.f
pyraysum/src/eigenvec.f
pyraysum/src/eispack-cg.f
pyraysum/src/matrixops.f
pyraysum/src/params.h
pyraysum/src/phaselist.f
pyraysum/src/raysum.f
pyraysum/src/readwrite.f
pyraysum/src/seis-spread.f
pyraysum/src/trace.f
pyraysum/tests/__init__.py
pyraysum/tests/test_0_imports.py
pyraysum/tests/test_1_model.py
pyraysum/tests/test_2_run_prs.py
pyraysum/tests/test_4_geometry.py
pyraysum/tests/test_5_control.py